{
    "configurations": [
        {
            "name": "Win32",
            "includePath": [
                "C:\\Program Files (x86)\\Arduino\\tools\\**",
                "C:\\Program Files (x86)\\Arduino\\hardware\\tools\\**",
                "C:\\Program Files (x86)\\Arduino\\hardware\\arduino\\avr\\**",
                "C:\\Users\\Jonathan\\AppData\\Local\\Arduino15\\packages\\esp32\\tools\\**",
                "C:\\Users\\Jonathan\\Documents\\Arduino\\libraries\\**",
                "C:\\Program Files (x86)\\Arduino\\libraries\\**",
                "C:\\Users\\Jonathan\\AppData\\Local\\Arduino15\\packages\\esp32\\hardware\\esp32\\1.0.4\\**"
            ],"forcedInclude": [
                "C:\\Program Files (x86)\\Arduino\\hardware\\arduino\\avr\\cores\\arduino\\Arduino.h" 
            ],
            "defines": [
                "_DEBUG",
                "UNICODE",
                "_UNICODE"
            ],
            "windowsSdkVersion": "10.0.18362.0",
            "compilerPath": "C:/Program Files (x86)/Microsoft Visual Studio/2019/BuildTools/VC/Tools/MSVC/14.27.29110/bin/Hostx64/x64/cl.exe",
            "intelliSenseMode": "windows-msvc-x64"
        }
    ],
    "version": 4
}